[
    {
        "id": "2444523",
        "channel": "VIP HBO 1 HD",
        "link": "https://list.iptvcat.com/my_list/s/ed5508baeb484c5c12583668f753c585.m3u8",
        "country": "netherlands",
        "liveliness": "72",
        "status": "offline",
        "lastChecked": "2022-03-21T00:00:00Z",
        "format": "fhd 2k",
        "mbps": "7004",
        "URI": [
            "s"
        ]
    },
    {
        "id": "2444524",
        "channel": "VIP HBO 2 HD",
        "link": "https://list.iptvcat.com/my_list/s/dfe38f802bd84d7acc72168005a9b29f.m3u8",
        "country": "netherlands",
        "liveliness": "72",
        "status": "offline",
        "lastChecked": "2022-03-21T00:00:00Z",
        "format": "fhd 2k",
        "mbps": "7004",
        "URI": [
            "s"
        ]
    },
    {
        "id": "2444525",
        "channel": "VIP HBO 3 HD",
        "link": "https://list.iptvcat.com/my_list/s/2f5b0fa09639a4bc35b3cfbff3c7020c.m3u8",
        "country": "netherlands",
        "liveliness": "72",
        "status": "offline",
        "lastChecked": "2022-03-21T00:00:00Z",
        "format": "fhd 2k",
        "mbps": "7004",
        "URI": [
            "s"
        ]
    },
    {
        "id": "2411946",
        "channel": "DISNEY CHANNEL HD",
        "link": "https://list.iptvcat.com/my_list/s/8253d28190af3a30a216c9f87eefba3e.m3u8",
        "country": "netherlands",
        "liveliness": "48",
        "status": "offline",
        "lastChecked": "2022-03-21T00:00:00Z",
        "format": "hd",
        "mbps": "5020",
        "URI": [
            "s"
        ]
    },
    {
        "id": "2444530",
        "channel": "DISNEY CHANNEL NEDERLAND",
        "link": "https://list.iptvcat.com/my_list/s/4ecca7cd8fe3d1cc5e3bd8a98f13ed09.m3u8",
        "country": "netherlands",
        "liveliness": "70",
        "status": "offline",
        "lastChecked": "2022-03-21T00:00:00Z",
        "format": "fhd 2k",
        "mbps": "7004",
        "URI": [
            "s"
        ]
    },
    {
        "id": "2444534",
        "channel": "DISNEY XD",
        "link": "https://list.iptvcat.com/my_list/s/d247657c9769708faf7590a9ce50d4bf.m3u8",
        "country": "netherlands",
        "liveliness": "71",
        "status": "offline",
        "lastChecked": "2022-03-21T00:00:00Z",
        "format": "fhd 2k",
        "mbps": "11126",
        "URI": [
            "s"
        ]
    },
    {
        "id": "2411947",
        "channel": "DISNEY XD / VERONICA HD",
        "link": "https://list.iptvcat.com/my_list/s/de84cebc2bf3811687aff1c8efda07b3.m3u8",
        "country": "netherlands",
        "liveliness": "50",
        "status": "offline",
        "lastChecked": "2022-03-21T00:00:00Z",
        "format": "hd",
        "mbps": "4825",
        "URI": [
            "s"
        ]
    },
    {
        "id": "2358810",
        "channel": "DISNEY XD / VERONICA HD",
        "link": "https://list.iptvcat.com/my_list/s/8127cab71a58cb2d39cae57655326446.m3u8",
        "country": "netherlands",
        "liveliness": "50",
        "status": "online",
        "lastChecked": "2022-03-21T00:00:00Z",
        "format": "hd",
        "mbps": "5020",
        "URI": [
            "s"
        ]
    },
    {
        "id": "2317737",
        "channel": "Disney XD",
        "link": "https://list.iptvcat.com/my_list/s/45d3d1aaf4ec7bf3e8aaa65ba979aaf6.m3u8",
        "country": "netherlands",
        "liveliness": "99",
        "status": "online",
        "lastChecked": "2022-03-21T00:00:00Z",
        "format": "hd",
        "mbps": "3188",
        "URI": [
            "s"
        ]
    },
    {
        "id": "2444527",
        "channel": "VERONICA/DISNEY XD FHD",
        "link": "https://list.iptvcat.com/my_list/s/ea70012cd7c8ccaf64d41a37ae434b8b.m3u8",
        "country": "netherlands",
        "liveliness": "73",
        "status": "offline",
        "lastChecked": "2022-03-21T00:00:00Z",
        "format": "fhd 2k",
        "mbps": "7004",
        "URI": [
            "s"
        ]
    },
    {
        "id": "2444629",
        "channel": "VIP DISNEY CHANNEL HD",
        "link": "https://list.iptvcat.com/my_list/s/d62f18cf0fd6f5cd578d2c36d38d543b.m3u8",
        "country": "netherlands",
        "liveliness": "63",
        "status": "offline",
        "lastChecked": "2022-03-21T00:00:00Z",
        "format": "hd",
        "mbps": "5020",
        "URI": [
            "s"
        ]
    },
    {
        "id": "2444695",
        "channel": "VIP DISNEY CHANNEL HEVC",
        "link": "https://list.iptvcat.com/my_list/s/22dcf47aef04966763682c9610a82b06.m3u8",
        "country": "netherlands",
        "liveliness": "59",
        "status": "offline",
        "lastChecked": "2022-03-21T00:00:00Z",
        "format": "fhd 2k",
        "mbps": "11126",
        "URI": [
            "s"
        ]
    },
    {
        "id": "2444691",
        "channel": "VIP Veronica/DisneyXD HEVC",
        "link": "https://list.iptvcat.com/my_list/s/6303981ba679aa13a5292cfb7635f241.m3u8",
        "country": "netherlands",
        "liveliness": "63",
        "status": "offline",
        "lastChecked": "2022-03-21T00:00:00Z",
        "format": "fhd 2k",
        "mbps": "11126",
        "URI": [
            "s"
        ]
    },
    {
        "id": "2448627",
        "channel": "Veronica/DisneyXD HD",
        "link": "https://list.iptvcat.com/my_list/s/5cc287fde0db0b2c1a6dc4f537f3983d.m3u8",
        "country": "netherlands",
        "liveliness": "23",
        "status": "offline",
        "lastChecked": "2022-03-21T00:00:00Z",
        "format": "hd",
        "mbps": "3188",
        "URI": [
            "s"
        ]
    }
]